{
  "generatedAt": "2026-05-28 12:28:15",
  "elapsedSec": 1959,
  "totalScreened": 88,
  "totalCandidates": 16,
  "totalPassed": 0,
  "params": {
    "pWin": 0.55,
    "gainMult": 1.5,
    "stopPct": 0.15,
    "mdd": 0.1,
    "capital": 1000000,
    "maxPosPct": 0.3,
    "highDropMin": 30.0,
    "lowRiseMax": 20.0,
    "perMax": 30.0,
    "cheapScoreMin": 2,
    "chipScoreMin": 2,
    "top10MinPct": 40.0,
    "minAvgVolume": 50,
    "minPrice": 5
  },
  "candidates": [
    {
      "sid": "2072",
      "sname": "世紀風電",
      "curPrice": 166.5,
      "avgVolume": 582.3,
      "instNet": 279.5,
      "chipScore": 2,
      "chipOk": true,
      "chipReasons": [
        "法人淨買超 ✓",
        "量縮回升 ✓",
        "尚未收斂 ✗"
      ],
      "cheapScore": 3,
      "cheapOk": true,
      "cheapReasons": [
        "距高點 48% ✓",
        "距低點 +2% ✓",
        "PER 12.7 ✓"
      ],
      "high6m": 321.0,
      "low3m": 162.5,
      "dropPct": 48.1,
      "risePct": 2.5,
      "per": 12.74,
      "top10Pct": null,
      "holderOk": false,
      "ev": 73.74,
      "rr": 6.19,
      "target": 321.0,
      "stop": 141.53,
      "evPass": true,
      "status": "candidate"
    },
    {
      "sid": "7792",
      "sname": "安葆",
      "curPrice": 256.0,
      "avgVolume": 227.9,
      "instNet": 17.2,
      "chipScore": 2,
      "chipOk": true,
      "chipReasons": [
        "法人淨買超 ✓",
        "量縮回升 ✓",
        "尚未收斂 ✗"
      ],
      "cheapScore": 2,
      "cheapOk": true,
      "cheapReasons": [
        "距高點 38% ✓",
        "距低點 +0% ✓",
        "PER 32.6 過高 ✗"
      ],
      "high6m": 415.0,
      "low3m": 255.5,
      "dropPct": 38.3,
      "risePct": 0.2,
      "per": 32.57,
      "top10Pct": null,
      "holderOk": false,
      "ev": 70.17,
      "rr": 4.14,
      "target": 415.0,
      "stop": 217.6,
      "evPass": true,
      "status": "candidate"
    },
    {
      "sid": "7820",
      "sname": "立盈",
      "curPrice": 126.5,
      "avgVolume": 77.6,
      "instNet": 1.1,
      "chipScore": 2,
      "chipOk": true,
      "chipReasons": [
        "法人淨買超 ✓",
        "量縮回升 ✓",
        "尚未收斂 ✗"
      ],
      "cheapScore": 2,
      "cheapOk": true,
      "cheapReasons": [
        "距高點 43% ✓",
        "距低點 +0% ✓",
        "PER 60.5 過高 ✗"
      ],
      "high6m": 221.5,
      "low3m": 126.0,
      "dropPct": 42.9,
      "risePct": 0.4,
      "per": 60.53,
      "top10Pct": null,
      "holderOk": false,
      "ev": 43.71,
      "rr": 5.01,
      "target": 221.5,
      "stop": 107.52,
      "evPass": true,
      "status": "candidate"
    },
    {
      "sid": "7714",
      "sname": "創泓科技",
      "curPrice": 114.5,
      "avgVolume": 82.1,
      "instNet": 0.4,
      "chipScore": 2,
      "chipOk": true,
      "chipReasons": [
        "法人淨買超 ✓",
        "量縮回升 ✓",
        "尚未收斂 ✗"
      ],
      "cheapScore": 3,
      "cheapOk": true,
      "cheapReasons": [
        "距高點 40% ✓",
        "距低點 +0% ✓",
        "PER 16.7 ✓"
      ],
      "high6m": 190.0,
      "low3m": 114.0,
      "dropPct": 39.7,
      "risePct": 0.4,
      "per": 16.67,
      "top10Pct": null,
      "holderOk": false,
      "ev": 33.8,
      "rr": 4.4,
      "target": 190.0,
      "stop": 97.33,
      "evPass": true,
      "status": "candidate"
    },
    {
      "sid": "7842",
      "sname": "天能綠電",
      "curPrice": 110.5,
      "avgVolume": 126.8,
      "instNet": -43.7,
      "chipScore": 2,
      "chipOk": true,
      "chipReasons": [
        "法人未買超 ✗",
        "量縮回升 ✓",
        "橫盤收斂 ✓"
      ],
      "cheapScore": 3,
      "cheapOk": true,
      "cheapReasons": [
        "距高點 40% ✓",
        "距低點 +12% ✓",
        "PER 25.1 ✓"
      ],
      "high6m": 185.0,
      "low3m": 99.0,
      "dropPct": 40.3,
      "risePct": 11.6,
      "per": 25.06,
      "top10Pct": null,
      "holderOk": false,
      "ev": 33.51,
      "rr": 4.49,
      "target": 185.0,
      "stop": 93.92,
      "evPass": true,
      "status": "candidate"
    },
    {
      "sid": "6467",
      "sname": "泰合",
      "curPrice": 122.5,
      "avgVolume": 243.0,
      "instNet": 5.0,
      "chipScore": 2,
      "chipOk": true,
      "chipReasons": [
        "法人淨買超 ✓",
        "量縮回升 ✓",
        "尚未收斂 ✗"
      ],
      "cheapScore": 2,
      "cheapOk": true,
      "cheapReasons": [
        "距高點 35% ✓",
        "距低點 +17% ✓",
        "無 PER 資料 —"
      ],
      "high6m": 187.5,
      "low3m": 104.5,
      "dropPct": 34.7,
      "risePct": 17.2,
      "per": null,
      "top10Pct": null,
      "holderOk": false,
      "ev": 27.48,
      "rr": 3.54,
      "target": 187.5,
      "stop": 104.12,
      "evPass": true,
      "status": "candidate"
    },
    {
      "sid": "7821",
      "sname": "神數",
      "curPrice": 42.95,
      "avgVolume": 215.7,
      "instNet": 154.9,
      "chipScore": 3,
      "chipOk": true,
      "chipReasons": [
        "法人淨買超 ✓",
        "量縮回升 ✓",
        "橫盤收斂 ✓"
      ],
      "cheapScore": 3,
      "cheapOk": true,
      "cheapReasons": [
        "距高點 44% ✓",
        "距低點 +1% ✓",
        "PER 14.4 ✓"
      ],
      "high6m": 76.9,
      "low3m": 42.7,
      "dropPct": 44.1,
      "risePct": 0.6,
      "per": 14.36,
      "top10Pct": null,
      "holderOk": false,
      "ev": 15.77,
      "rr": 5.27,
      "target": 76.9,
      "stop": 36.51,
      "evPass": true,
      "status": "candidate"
    },
    {
      "sid": "7876",
      "sname": "鼎晉生技",
      "curPrice": 36.5,
      "avgVolume": 148.1,
      "instNet": 2.0,
      "chipScore": 2,
      "chipOk": true,
      "chipReasons": [
        "法人淨買超 ✓",
        "量縮回升 ✓",
        "尚未收斂 ✗"
      ],
      "cheapScore": 2,
      "cheapOk": true,
      "cheapReasons": [
        "距高點 47% ✓",
        "距低點 +8% ✓",
        "無 PER 資料 —"
      ],
      "high6m": 69.0,
      "low3m": 33.85,
      "dropPct": 47.1,
      "risePct": 7.8,
      "per": null,
      "top10Pct": null,
      "holderOk": false,
      "ev": 15.41,
      "rr": 5.93,
      "target": 69.0,
      "stop": 31.02,
      "evPass": true,
      "status": "candidate"
    },
    {
      "sid": "7703",
      "sname": "銳澤",
      "curPrice": 206.5,
      "avgVolume": 219.0,
      "instNet": 77.0,
      "chipScore": 2,
      "chipOk": true,
      "chipReasons": [
        "法人淨買超 ✓",
        "量縮回升 ✓",
        "尚未收斂 ✗"
      ],
      "cheapScore": 2,
      "cheapOk": true,
      "cheapReasons": [
        "距高點僅 20% ✗",
        "距低點 +12% ✓",
        "PER 26.3 ✓"
      ],
      "high6m": 258.0,
      "low3m": 185.0,
      "dropPct": 20.0,
      "risePct": 11.6,
      "per": 26.34,
      "top10Pct": null,
      "holderOk": false,
      "ev": 14.39,
      "rr": 1.66,
      "target": 258.0,
      "stop": 175.53,
      "evPass": true,
      "status": "candidate"
    },
    {
      "sid": "7547",
      "sname": "碩網",
      "curPrice": 61.0,
      "avgVolume": 422.1,
      "instNet": 41.0,
      "chipScore": 2,
      "chipOk": true,
      "chipReasons": [
        "法人淨買超 ✓",
        "量縮回升 ✓",
        "尚未收斂 ✗"
      ],
      "cheapScore": 2,
      "cheapOk": true,
      "cheapReasons": [
        "距高點 35% ✓",
        "距低點 +22% ✗",
        "PER 24.7 ✓"
      ],
      "high6m": 94.2,
      "low3m": 49.9,
      "dropPct": 35.2,
      "risePct": 22.2,
      "per": 24.7,
      "top10Pct": null,
      "holderOk": false,
      "ev": 14.14,
      "rr": 3.63,
      "target": 94.2,
      "stop": 51.85,
      "evPass": true,
      "status": "candidate"
    },
    {
      "sid": "7784",
      "sname": "安邦生技*",
      "curPrice": 9.89,
      "avgVolume": 709.8,
      "instNet": 0.0,
      "chipScore": 2,
      "chipOk": true,
      "chipReasons": [
        "無法人資料 —",
        "量縮回升 ✓",
        "橫盤收斂 ✓"
      ],
      "cheapScore": 2,
      "cheapOk": true,
      "cheapReasons": [
        "距高點 56% ✓",
        "距低點 +16% ✓",
        "無 PER 資料 —"
      ],
      "high6m": 22.45,
      "low3m": 8.5,
      "dropPct": 55.9,
      "risePct": 16.4,
      "per": null,
      "top10Pct": null,
      "holderOk": false,
      "ev": 6.24,
      "rr": 8.49,
      "target": 22.45,
      "stop": 8.41,
      "evPass": true,
      "status": "candidate"
    },
    {
      "sid": "6555",
      "sname": "榮炭",
      "curPrice": 20.75,
      "avgVolume": 183.6,
      "instNet": -43.8,
      "chipScore": 2,
      "chipOk": true,
      "chipReasons": [
        "法人未買超 ✗",
        "量縮回升 ✓",
        "橫盤收斂 ✓"
      ],
      "cheapScore": 2,
      "cheapOk": true,
      "cheapReasons": [
        "距高點 38% ✓",
        "距低點 +8% ✓",
        "無 PER 資料 —"
      ],
      "high6m": 33.25,
      "low3m": 19.2,
      "dropPct": 37.6,
      "risePct": 8.1,
      "per": null,
      "top10Pct": null,
      "holderOk": false,
      "ev": 5.48,
      "rr": 4.02,
      "target": 33.25,
      "stop": 17.64,
      "evPass": true,
      "status": "candidate"
    },
    {
      "sid": "7882",
      "sname": "倍利創投",
      "curPrice": 21.6,
      "avgVolume": 208.3,
      "instNet": -2.0,
      "chipScore": 2,
      "chipOk": true,
      "chipReasons": [
        "法人未買超 ✗",
        "量縮回升 ✓",
        "橫盤收斂 ✓"
      ],
      "cheapScore": 2,
      "cheapOk": true,
      "cheapReasons": [
        "距高點 36% ✓",
        "距低點 +1% ✓",
        "無 PER 資料 —"
      ],
      "high6m": 33.55,
      "low3m": 21.3,
      "dropPct": 35.6,
      "risePct": 1.4,
      "per": null,
      "top10Pct": null,
      "holderOk": false,
      "ev": 5.11,
      "rr": 3.69,
      "target": 33.55,
      "stop": 18.36,
      "evPass": true,
      "status": "candidate"
    },
    {
      "sid": "6580",
      "sname": "台睿",
      "curPrice": 14.95,
      "avgVolume": 141.4,
      "instNet": -4.0,
      "chipScore": 2,
      "chipOk": true,
      "chipReasons": [
        "法人未買超 ✗",
        "量縮回升 ✓",
        "橫盤收斂 ✓"
      ],
      "cheapScore": 2,
      "cheapOk": true,
      "cheapReasons": [
        "距高點 37% ✓",
        "距低點 +10% ✓",
        "無 PER 資料 —"
      ],
      "high6m": 23.6,
      "low3m": 13.55,
      "dropPct": 36.7,
      "risePct": 10.3,
      "per": null,
      "top10Pct": null,
      "holderOk": false,
      "ev": 3.75,
      "rr": 3.86,
      "target": 23.6,
      "stop": 12.71,
      "evPass": true,
      "status": "candidate"
    },
    {
      "sid": "6677",
      "sname": "瑩碩生技",
      "curPrice": 17.7,
      "avgVolume": 81.8,
      "instNet": 0.0,
      "chipScore": 2,
      "chipOk": true,
      "chipReasons": [
        "無法人資料 —",
        "量縮回升 ✓",
        "橫盤收斂 ✓"
      ],
      "cheapScore": 2,
      "cheapOk": true,
      "cheapReasons": [
        "距高點 30% ✓",
        "距低點 +3% ✓",
        "無 PER 資料 —"
      ],
      "high6m": 25.3,
      "low3m": 17.2,
      "dropPct": 30.0,
      "risePct": 2.9,
      "per": null,
      "top10Pct": null,
      "holderOk": false,
      "ev": 2.98,
      "rr": 2.86,
      "target": 25.3,
      "stop": 15.04,
      "evPass": true,
      "status": "candidate"
    },
    {
      "sid": "2248",
      "sname": "華勝-KY",
      "curPrice": 54.7,
      "avgVolume": 59.3,
      "instNet": -9.0,
      "chipScore": 2,
      "chipOk": true,
      "chipReasons": [
        "法人未買超 ✗",
        "量縮回升 ✓",
        "橫盤收斂 ✓"
      ],
      "cheapScore": 2,
      "cheapOk": true,
      "cheapReasons": [
        "距高點僅 12% ✗",
        "距低點 +19% ✓",
        "PER 9.2 ✓"
      ],
      "high6m": 62.1,
      "low3m": 46.1,
      "dropPct": 11.9,
      "risePct": 18.7,
      "per": 9.24,
      "top10Pct": null,
      "holderOk": false,
      "ev": 0.38,
      "rr": 0.9,
      "target": 62.1,
      "stop": 46.5,
      "evPass": true,
      "status": "candidate"
    }
  ],
  "all": [
    {
      "sid": "7821",
      "sname": "神數",
      "curPrice": 42.95,
      "avgVolume": 215.7,
      "instNet": 154.9,
      "chipScore": 3,
      "chipOk": true,
      "chipReasons": [
        "法人淨買超 ✓",
        "量縮回升 ✓",
        "橫盤收斂 ✓"
      ],
      "cheapScore": 3,
      "cheapOk": true,
      "cheapReasons": [
        "距高點 44% ✓",
        "距低點 +1% ✓",
        "PER 14.4 ✓"
      ],
      "high6m": 76.9,
      "low3m": 42.7,
      "dropPct": 44.1,
      "risePct": 0.6,
      "per": 14.36,
      "top10Pct": null,
      "holderOk": false,
      "ev": 15.77,
      "rr": 5.27,
      "target": 76.9,
      "stop": 36.51,
      "evPass": true,
      "status": "candidate"
    },
    {
      "sid": "7728",
      "sname": "光焱科技",
      "curPrice": 778.0,
      "avgVolume": 126.6,
      "instNet": 7.9,
      "chipScore": 3,
      "chipOk": true,
      "chipReasons": [
        "法人淨買超 ✓",
        "量縮回升 ✓",
        "橫盤收斂 ✓"
      ],
      "cheapScore": 1,
      "cheapOk": false,
      "cheapReasons": [
        "距高點僅 21% ✗",
        "距低點 +20% ✓",
        "PER 144.9 過高 ✗"
      ],
      "high6m": 980.0,
      "low3m": 650.0,
      "dropPct": 20.6,
      "risePct": 19.7,
      "per": 144.88,
      "top10Pct": null,
      "holderOk": false,
      "ev": 58.58,
      "rr": 1.73,
      "target": 980.0,
      "stop": 661.3,
      "evPass": true,
      "status": "fail"
    },
    {
      "sid": "5297",
      "sname": "廣化",
      "curPrice": 126.5,
      "avgVolume": 1378.0,
      "instNet": 36.1,
      "chipScore": 3,
      "chipOk": true,
      "chipReasons": [
        "法人淨買超 ✓",
        "量縮回升 ✓",
        "橫盤收斂 ✓"
      ],
      "cheapScore": 1,
      "cheapOk": false,
      "cheapReasons": [
        "距高點 60% ✓",
        "距低點 +369% ✗",
        "無 PER 資料 —"
      ],
      "high6m": 313.5,
      "low3m": 27.0,
      "dropPct": 59.6,
      "risePct": 368.5,
      "per": null,
      "top10Pct": null,
      "holderOk": false,
      "ev": 94.31,
      "rr": 9.85,
      "target": 313.5,
      "stop": 107.52,
      "evPass": true,
      "status": "fail"
    },
    {
      "sid": "6027",
      "sname": "德信",
      "curPrice": 12.6,
      "avgVolume": 72.5,
      "instNet": 6.0,
      "chipScore": 3,
      "chipOk": true,
      "chipReasons": [
        "法人淨買超 ✓",
        "量縮回升 ✓",
        "橫盤收斂 ✓"
      ],
      "cheapScore": 0,
      "cheapOk": false,
      "cheapReasons": [
        "距高點僅 13% ✗",
        "距低點 +40% ✗",
        "無 PER 資料 —"
      ],
      "high6m": 14.5,
      "low3m": 9.0,
      "dropPct": 13.1,
      "risePct": 40.0,
      "per": null,
      "top10Pct": null,
      "holderOk": false,
      "ev": 0.19,
      "rr": 1.01,
      "target": 14.5,
      "stop": 10.71,
      "evPass": true,
      "status": "fail"
    },
    {
      "sid": "7911",
      "sname": "阿波羅電力",
      "curPrice": 120.0,
      "avgVolume": 169.3,
      "instNet": 4.9,
      "chipScore": 3,
      "chipOk": true,
      "chipReasons": [
        "法人淨買超 ✓",
        "量縮回升 ✓",
        "橫盤收斂 ✓"
      ],
      "cheapScore": 0,
      "cheapOk": false,
      "cheapReasons": [
        "距高點僅 29% ✗",
        "距低點 +50% ✗",
        "無 PER 資料 —"
      ],
      "high6m": 169.0,
      "low3m": 80.0,
      "dropPct": 29.0,
      "risePct": 50.0,
      "per": null,
      "top10Pct": null,
      "holderOk": false,
      "ev": 18.85,
      "rr": 2.72,
      "target": 169.0,
      "stop": 102.0,
      "evPass": true,
      "status": "fail"
    },
    {
      "sid": "7854",
      "sname": "佐茂",
      "curPrice": 96.8,
      "avgVolume": 183.7,
      "instNet": 2.0,
      "chipScore": 3,
      "chipOk": true,
      "chipReasons": [
        "法人淨買超 ✓",
        "量縮回升 ✓",
        "橫盤收斂 ✓"
      ],
      "cheapScore": 0,
      "cheapOk": false,
      "cheapReasons": [
        "距高點僅 28% ✗",
        "距低點 +67% ✗",
        "無 PER 資料 —"
      ],
      "high6m": 134.0,
      "low3m": 57.8,
      "dropPct": 27.8,
      "risePct": 67.5,
      "per": null,
      "top10Pct": null,
      "holderOk": false,
      "ev": 13.93,
      "rr": 2.56,
      "target": 134.0,
      "stop": 82.28,
      "evPass": true,
      "status": "fail"
    },
    {
      "sid": "6676",
      "sname": "祥翊",
      "curPrice": 13.75,
      "avgVolume": 332.7,
      "instNet": 3.0,
      "chipScore": 3,
      "chipOk": true,
      "chipReasons": [
        "法人淨買超 ✓",
        "量縮回升 ✓",
        "橫盤收斂 ✓"
      ],
      "cheapScore": 1,
      "cheapOk": false,
      "cheapReasons": [
        "距高點僅 28% ✗",
        "距低點 +5% ✓",
        "無 PER 資料 —"
      ],
      "high6m": 19.1,
      "low3m": 13.05,
      "dropPct": 28.0,
      "risePct": 5.4,
      "per": null,
      "top10Pct": null,
      "holderOk": false,
      "ev": 2.02,
      "rr": 2.6,
      "target": 19.1,
      "stop": 11.69,
      "evPass": true,
      "status": "fail"
    },
    {
      "sid": "7703",
      "sname": "銳澤",
      "curPrice": 206.5,
      "avgVolume": 219.0,
      "instNet": 77.0,
      "chipScore": 2,
      "chipOk": true,
      "chipReasons": [
        "法人淨買超 ✓",
        "量縮回升 ✓",
        "尚未收斂 ✗"
      ],
      "cheapScore": 2,
      "cheapOk": true,
      "cheapReasons": [
        "距高點僅 20% ✗",
        "距低點 +12% ✓",
        "PER 26.3 ✓"
      ],
      "high6m": 258.0,
      "low3m": 185.0,
      "dropPct": 20.0,
      "risePct": 11.6,
      "per": 26.34,
      "top10Pct": null,
      "holderOk": false,
      "ev": 14.39,
      "rr": 1.66,
      "target": 258.0,
      "stop": 175.53,
      "evPass": true,
      "status": "candidate"
    },
    {
      "sid": "7714",
      "sname": "創泓科技",
      "curPrice": 114.5,
      "avgVolume": 82.1,
      "instNet": 0.4,
      "chipScore": 2,
      "chipOk": true,
      "chipReasons": [
        "法人淨買超 ✓",
        "量縮回升 ✓",
        "尚未收斂 ✗"
      ],
      "cheapScore": 3,
      "cheapOk": true,
      "cheapReasons": [
        "距高點 40% ✓",
        "距低點 +0% ✓",
        "PER 16.7 ✓"
      ],
      "high6m": 190.0,
      "low3m": 114.0,
      "dropPct": 39.7,
      "risePct": 0.4,
      "per": 16.67,
      "top10Pct": null,
      "holderOk": false,
      "ev": 33.8,
      "rr": 4.4,
      "target": 190.0,
      "stop": 97.33,
      "evPass": true,
      "status": "candidate"
    },
    {
      "sid": "2248",
      "sname": "華勝-KY",
      "curPrice": 54.7,
      "avgVolume": 59.3,
      "instNet": -9.0,
      "chipScore": 2,
      "chipOk": true,
      "chipReasons": [
        "法人未買超 ✗",
        "量縮回升 ✓",
        "橫盤收斂 ✓"
      ],
      "cheapScore": 2,
      "cheapOk": true,
      "cheapReasons": [
        "距高點僅 12% ✗",
        "距低點 +19% ✓",
        "PER 9.2 ✓"
      ],
      "high6m": 62.1,
      "low3m": 46.1,
      "dropPct": 11.9,
      "risePct": 18.7,
      "per": 9.24,
      "top10Pct": null,
      "holderOk": false,
      "ev": 0.38,
      "rr": 0.9,
      "target": 62.1,
      "stop": 46.5,
      "evPass": true,
      "status": "candidate"
    },
    {
      "sid": "7547",
      "sname": "碩網",
      "curPrice": 61.0,
      "avgVolume": 422.1,
      "instNet": 41.0,
      "chipScore": 2,
      "chipOk": true,
      "chipReasons": [
        "法人淨買超 ✓",
        "量縮回升 ✓",
        "尚未收斂 ✗"
      ],
      "cheapScore": 2,
      "cheapOk": true,
      "cheapReasons": [
        "距高點 35% ✓",
        "距低點 +22% ✗",
        "PER 24.7 ✓"
      ],
      "high6m": 94.2,
      "low3m": 49.9,
      "dropPct": 35.2,
      "risePct": 22.2,
      "per": 24.7,
      "top10Pct": null,
      "holderOk": false,
      "ev": 14.14,
      "rr": 3.63,
      "target": 94.2,
      "stop": 51.85,
      "evPass": true,
      "status": "candidate"
    },
    {
      "sid": "7792",
      "sname": "安葆",
      "curPrice": 256.0,
      "avgVolume": 227.9,
      "instNet": 17.2,
      "chipScore": 2,
      "chipOk": true,
      "chipReasons": [
        "法人淨買超 ✓",
        "量縮回升 ✓",
        "尚未收斂 ✗"
      ],
      "cheapScore": 2,
      "cheapOk": true,
      "cheapReasons": [
        "距高點 38% ✓",
        "距低點 +0% ✓",
        "PER 32.6 過高 ✗"
      ],
      "high6m": 415.0,
      "low3m": 255.5,
      "dropPct": 38.3,
      "risePct": 0.2,
      "per": 32.57,
      "top10Pct": null,
      "holderOk": false,
      "ev": 70.17,
      "rr": 4.14,
      "target": 415.0,
      "stop": 217.6,
      "evPass": true,
      "status": "candidate"
    },
    {
      "sid": "2072",
      "sname": "世紀風電",
      "curPrice": 166.5,
      "avgVolume": 582.3,
      "instNet": 279.5,
      "chipScore": 2,
      "chipOk": true,
      "chipReasons": [
        "法人淨買超 ✓",
        "量縮回升 ✓",
        "尚未收斂 ✗"
      ],
      "cheapScore": 3,
      "cheapOk": true,
      "cheapReasons": [
        "距高點 48% ✓",
        "距低點 +2% ✓",
        "PER 12.7 ✓"
      ],
      "high6m": 321.0,
      "low3m": 162.5,
      "dropPct": 48.1,
      "risePct": 2.5,
      "per": 12.74,
      "top10Pct": null,
      "holderOk": false,
      "ev": 73.74,
      "rr": 6.19,
      "target": 321.0,
      "stop": 141.53,
      "evPass": true,
      "status": "candidate"
    },
    {
      "sid": "7820",
      "sname": "立盈",
      "curPrice": 126.5,
      "avgVolume": 77.6,
      "instNet": 1.1,
      "chipScore": 2,
      "chipOk": true,
      "chipReasons": [
        "法人淨買超 ✓",
        "量縮回升 ✓",
        "尚未收斂 ✗"
      ],
      "cheapScore": 2,
      "cheapOk": true,
      "cheapReasons": [
        "距高點 43% ✓",
        "距低點 +0% ✓",
        "PER 60.5 過高 ✗"
      ],
      "high6m": 221.5,
      "low3m": 126.0,
      "dropPct": 42.9,
      "risePct": 0.4,
      "per": 60.53,
      "top10Pct": null,
      "holderOk": false,
      "ev": 43.71,
      "rr": 5.01,
      "target": 221.5,
      "stop": 107.52,
      "evPass": true,
      "status": "candidate"
    },
    {
      "sid": "7842",
      "sname": "天能綠電",
      "curPrice": 110.5,
      "avgVolume": 126.8,
      "instNet": -43.7,
      "chipScore": 2,
      "chipOk": true,
      "chipReasons": [
        "法人未買超 ✗",
        "量縮回升 ✓",
        "橫盤收斂 ✓"
      ],
      "cheapScore": 3,
      "cheapOk": true,
      "cheapReasons": [
        "距高點 40% ✓",
        "距低點 +12% ✓",
        "PER 25.1 ✓"
      ],
      "high6m": 185.0,
      "low3m": 99.0,
      "dropPct": 40.3,
      "risePct": 11.6,
      "per": 25.06,
      "top10Pct": null,
      "holderOk": false,
      "ev": 33.51,
      "rr": 4.49,
      "target": 185.0,
      "stop": 93.92,
      "evPass": true,
      "status": "candidate"
    },
    {
      "sid": "6555",
      "sname": "榮炭",
      "curPrice": 20.75,
      "avgVolume": 183.6,
      "instNet": -43.8,
      "chipScore": 2,
      "chipOk": true,
      "chipReasons": [
        "法人未買超 ✗",
        "量縮回升 ✓",
        "橫盤收斂 ✓"
      ],
      "cheapScore": 2,
      "cheapOk": true,
      "cheapReasons": [
        "距高點 38% ✓",
        "距低點 +8% ✓",
        "無 PER 資料 —"
      ],
      "high6m": 33.25,
      "low3m": 19.2,
      "dropPct": 37.6,
      "risePct": 8.1,
      "per": null,
      "top10Pct": null,
      "holderOk": false,
      "ev": 5.48,
      "rr": 4.02,
      "target": 33.25,
      "stop": 17.64,
      "evPass": true,
      "status": "candidate"
    },
    {
      "sid": "6580",
      "sname": "台睿",
      "curPrice": 14.95,
      "avgVolume": 141.4,
      "instNet": -4.0,
      "chipScore": 2,
      "chipOk": true,
      "chipReasons": [
        "法人未買超 ✗",
        "量縮回升 ✓",
        "橫盤收斂 ✓"
      ],
      "cheapScore": 2,
      "cheapOk": true,
      "cheapReasons": [
        "距高點 37% ✓",
        "距低點 +10% ✓",
        "無 PER 資料 —"
      ],
      "high6m": 23.6,
      "low3m": 13.55,
      "dropPct": 36.7,
      "risePct": 10.3,
      "per": null,
      "top10Pct": null,
      "holderOk": false,
      "ev": 3.75,
      "rr": 3.86,
      "target": 23.6,
      "stop": 12.71,
      "evPass": true,
      "status": "candidate"
    },
    {
      "sid": "6467",
      "sname": "泰合",
      "curPrice": 122.5,
      "avgVolume": 243.0,
      "instNet": 5.0,
      "chipScore": 2,
      "chipOk": true,
      "chipReasons": [
        "法人淨買超 ✓",
        "量縮回升 ✓",
        "尚未收斂 ✗"
      ],
      "cheapScore": 2,
      "cheapOk": true,
      "cheapReasons": [
        "距高點 35% ✓",
        "距低點 +17% ✓",
        "無 PER 資料 —"
      ],
      "high6m": 187.5,
      "low3m": 104.5,
      "dropPct": 34.7,
      "risePct": 17.2,
      "per": null,
      "top10Pct": null,
      "holderOk": false,
      "ev": 27.48,
      "rr": 3.54,
      "target": 187.5,
      "stop": 104.12,
      "evPass": true,
      "status": "candidate"
    },
    {
      "sid": "7882",
      "sname": "倍利創投",
      "curPrice": 21.6,
      "avgVolume": 208.3,
      "instNet": -2.0,
      "chipScore": 2,
      "chipOk": true,
      "chipReasons": [
        "法人未買超 ✗",
        "量縮回升 ✓",
        "橫盤收斂 ✓"
      ],
      "cheapScore": 2,
      "cheapOk": true,
      "cheapReasons": [
        "距高點 36% ✓",
        "距低點 +1% ✓",
        "無 PER 資料 —"
      ],
      "high6m": 33.55,
      "low3m": 21.3,
      "dropPct": 35.6,
      "risePct": 1.4,
      "per": null,
      "top10Pct": null,
      "holderOk": false,
      "ev": 5.11,
      "rr": 3.69,
      "target": 33.55,
      "stop": 18.36,
      "evPass": true,
      "status": "candidate"
    },
    {
      "sid": "7876",
      "sname": "鼎晉生技",
      "curPrice": 36.5,
      "avgVolume": 148.1,
      "instNet": 2.0,
      "chipScore": 2,
      "chipOk": true,
      "chipReasons": [
        "法人淨買超 ✓",
        "量縮回升 ✓",
        "尚未收斂 ✗"
      ],
      "cheapScore": 2,
      "cheapOk": true,
      "cheapReasons": [
        "距高點 47% ✓",
        "距低點 +8% ✓",
        "無 PER 資料 —"
      ],
      "high6m": 69.0,
      "low3m": 33.85,
      "dropPct": 47.1,
      "risePct": 7.8,
      "per": null,
      "top10Pct": null,
      "holderOk": false,
      "ev": 15.41,
      "rr": 5.93,
      "target": 69.0,
      "stop": 31.02,
      "evPass": true,
      "status": "candidate"
    },
    {
      "sid": "7784",
      "sname": "安邦生技*",
      "curPrice": 9.89,
      "avgVolume": 709.8,
      "instNet": 0.0,
      "chipScore": 2,
      "chipOk": true,
      "chipReasons": [
        "無法人資料 —",
        "量縮回升 ✓",
        "橫盤收斂 ✓"
      ],
      "cheapScore": 2,
      "cheapOk": true,
      "cheapReasons": [
        "距高點 56% ✓",
        "距低點 +16% ✓",
        "無 PER 資料 —"
      ],
      "high6m": 22.45,
      "low3m": 8.5,
      "dropPct": 55.9,
      "risePct": 16.4,
      "per": null,
      "top10Pct": null,
      "holderOk": false,
      "ev": 6.24,
      "rr": 8.49,
      "target": 22.45,
      "stop": 8.41,
      "evPass": true,
      "status": "candidate"
    },
    {
      "sid": "6677",
      "sname": "瑩碩生技",
      "curPrice": 17.7,
      "avgVolume": 81.8,
      "instNet": 0.0,
      "chipScore": 2,
      "chipOk": true,
      "chipReasons": [
        "無法人資料 —",
        "量縮回升 ✓",
        "橫盤收斂 ✓"
      ],
      "cheapScore": 2,
      "cheapOk": true,
      "cheapReasons": [
        "距高點 30% ✓",
        "距低點 +3% ✓",
        "無 PER 資料 —"
      ],
      "high6m": 25.3,
      "low3m": 17.2,
      "dropPct": 30.0,
      "risePct": 2.9,
      "per": null,
      "top10Pct": null,
      "holderOk": false,
      "ev": 2.98,
      "rr": 2.86,
      "target": 25.3,
      "stop": 15.04,
      "evPass": true,
      "status": "candidate"
    },
    {
      "sid": "1563",
      "sname": "巧新",
      "curPrice": 61.1,
      "avgVolume": 1258.0,
      "instNet": 877.3,
      "chipScore": 2,
      "chipOk": true,
      "chipReasons": [
        "法人淨買超 ✓",
        "量縮回升 ✓",
        "尚未收斂 ✗"
      ],
      "cheapScore": 0,
      "cheapOk": false,
      "cheapReasons": [
        "距高點僅 0% ✗",
        "距低點 +55% ✗",
        "PER 138.9 過高 ✗"
      ],
      "high6m": 61.1,
      "low3m": 39.35,
      "dropPct": 0.0,
      "risePct": 55.3,
      "per": 138.86,
      "top10Pct": null,
      "holderOk": false,
      "ev": -4.12,
      "rr": 0.0,
      "target": 61.1,
      "stop": 51.94,
      "evPass": false,
      "status": "fail"
    },
    {
      "sid": "6903",
      "sname": "巨漢",
      "curPrice": 399.5,
      "avgVolume": 1312.9,
      "instNet": 196.8,
      "chipScore": 2,
      "chipOk": true,
      "chipReasons": [
        "法人淨買超 ✓",
        "量縮回升 ✓",
        "尚未收斂 ✗"
      ],
      "cheapScore": 1,
      "cheapOk": false,
      "cheapReasons": [
        "距高點僅 12% ✗",
        "距低點 +54% ✗",
        "PER 24.6 ✓"
      ],
      "high6m": 451.5,
      "low3m": 260.0,
      "dropPct": 11.5,
      "risePct": 53.7,
      "per": 24.63,
      "top10Pct": null,
      "holderOk": false,
      "ev": 1.63,
      "rr": 0.87,
      "target": 451.5,
      "stop": 339.57,
      "evPass": true,
      "status": "fail"
    },
    {
      "sid": "7805",
      "sname": "威聯通",
      "curPrice": 785.0,
      "avgVolume": 181.0,
      "instNet": 414.7,
      "chipScore": 2,
      "chipOk": true,
      "chipReasons": [
        "法人淨買超 ✓",
        "量縮回升 ✓",
        "尚未收斂 ✗"
      ],
      "cheapScore": 1,
      "cheapOk": false,
      "cheapReasons": [
        "距高點僅 7% ✗",
        "距低點 +40% ✗",
        "PER 18.2 ✓"
      ],
      "high6m": 846.0,
      "low3m": 562.0,
      "dropPct": 7.2,
      "risePct": 39.7,
      "per": 18.19,
      "top10Pct": null,
      "holderOk": false,
      "ev": -19.44,
      "rr": 0.52,
      "target": 846.0,
      "stop": 667.25,
      "evPass": false,
      "status": "fail"
    },
    {
      "sid": "7805",
      "sname": "威聯通",
      "curPrice": 785.0,
      "avgVolume": 181.0,
      "instNet": 414.7,
      "chipScore": 2,
      "chipOk": true,
      "chipReasons": [
        "法人淨買超 ✓",
        "量縮回升 ✓",
        "尚未收斂 ✗"
      ],
      "cheapScore": 1,
      "cheapOk": false,
      "cheapReasons": [
        "距高點僅 7% ✗",
        "距低點 +40% ✗",
        "PER 18.2 ✓"
      ],
      "high6m": 846.0,
      "low3m": 562.0,
      "dropPct": 7.2,
      "risePct": 39.7,
      "per": 18.19,
      "top10Pct": null,
      "holderOk": false,
      "ev": -19.44,
      "rr": 0.52,
      "target": 846.0,
      "stop": 667.25,
      "evPass": false,
      "status": "fail"
    },
    {
      "sid": "7893",
      "sname": "睿信",
      "curPrice": 201.0,
      "avgVolume": 71.4,
      "instNet": 3.0,
      "chipScore": 2,
      "chipOk": true,
      "chipReasons": [
        "法人淨買超 ✓",
        "量縮回升 ✓",
        "尚未收斂 ✗"
      ],
      "cheapScore": 0,
      "cheapOk": false,
      "cheapReasons": [
        "距高點僅 26% ✗",
        "距低點 +24% ✗",
        "無 PER 資料 —"
      ],
      "high6m": 270.0,
      "low3m": 162.0,
      "dropPct": 25.6,
      "risePct": 24.1,
      "per": null,
      "top10Pct": null,
      "holderOk": false,
      "ev": 24.38,
      "rr": 2.29,
      "target": 270.0,
      "stop": 170.85,
      "evPass": true,
      "status": "fail"
    },
    {
      "sid": "3485",
      "sname": "敘豐",
      "curPrice": 340.0,
      "avgVolume": 681.4,
      "instNet": 91.5,
      "chipScore": 2,
      "chipOk": true,
      "chipReasons": [
        "法人淨買超 ✓",
        "量縮回升 ✓",
        "尚未收斂 ✗"
      ],
      "cheapScore": 0,
      "cheapOk": false,
      "cheapReasons": [
        "距高點僅 13% ✗",
        "距低點 +106% ✗",
        "PER 65.8 過高 ✗"
      ],
      "high6m": 389.0,
      "low3m": 165.0,
      "dropPct": 12.6,
      "risePct": 106.1,
      "per": 65.76,
      "top10Pct": null,
      "holderOk": false,
      "ev": 4.0,
      "rr": 0.96,
      "target": 389.0,
      "stop": 289.0,
      "evPass": true,
      "status": "fail"
    },
    {
      "sid": "6559",
      "sname": "研晶",
      "curPrice": 20.8,
      "avgVolume": 239.3,
      "instNet": 12.0,
      "chipScore": 2,
      "chipOk": true,
      "chipReasons": [
        "法人淨買超 ✓",
        "量縮回升 ✓",
        "尚未收斂 ✗"
      ],
      "cheapScore": 1,
      "cheapOk": false,
      "cheapReasons": [
        "距高點 61% ✓",
        "距低點 +85% ✗",
        "無 PER 資料 —"
      ],
      "high6m": 53.4,
      "low3m": 11.25,
      "dropPct": 61.0,
      "risePct": 84.9,
      "per": null,
      "top10Pct": null,
      "holderOk": false,
      "ev": 16.53,
      "rr": 10.45,
      "target": 53.4,
      "stop": 17.68,
      "evPass": true,
      "status": "fail"
    },
    {
      "sid": "6586",
      "sname": "醣基",
      "curPrice": 64.8,
      "avgVolume": 823.5,
      "instNet": -101.9,
      "chipScore": 2,
      "chipOk": true,
      "chipReasons": [
        "法人未買超 ✗",
        "量縮回升 ✓",
        "橫盤收斂 ✓"
      ],
      "cheapScore": 0,
      "cheapOk": false,
      "cheapReasons": [
        "距高點僅 12% ✗",
        "距低點 +185% ✗",
        "無 PER 資料 —"
      ],
      "high6m": 73.4,
      "low3m": 22.75,
      "dropPct": 11.7,
      "risePct": 184.8,
      "per": null,
      "top10Pct": null,
      "holderOk": false,
      "ev": 0.36,
      "rr": 0.88,
      "target": 73.4,
      "stop": 55.08,
      "evPass": true,
      "status": "fail"
    },
    {
      "sid": "6563",
      "sname": "映智",
      "curPrice": 30.7,
      "avgVolume": 203.7,
      "instNet": -5.0,
      "chipScore": 2,
      "chipOk": true,
      "chipReasons": [
        "法人未買超 ✗",
        "量縮回升 ✓",
        "橫盤收斂 ✓"
      ],
      "cheapScore": 0,
      "cheapOk": false,
      "cheapReasons": [
        "距高點僅 19% ✗",
        "距低點 +33% ✗",
        "無 PER 資料 —"
      ],
      "high6m": 38.1,
      "low3m": 23.0,
      "dropPct": 19.4,
      "risePct": 33.5,
      "per": null,
      "top10Pct": null,
      "holderOk": false,
      "ev": 2.0,
      "rr": 1.61,
      "target": 38.1,
      "stop": 26.09,
      "evPass": true,
      "status": "fail"
    },
    {
      "sid": "6565",
      "sname": "物聯",
      "curPrice": 20.25,
      "avgVolume": 140.3,
      "instNet": 0.0,
      "chipScore": 2,
      "chipOk": true,
      "chipReasons": [
        "法人未買超 ✗",
        "量縮回升 ✓",
        "橫盤收斂 ✓"
      ],
      "cheapScore": 1,
      "cheapOk": false,
      "cheapReasons": [
        "距高點 44% ✓",
        "距低點 +45% ✗",
        "無 PER 資料 —"
      ],
      "high6m": 36.3,
      "low3m": 14.0,
      "dropPct": 44.2,
      "risePct": 44.6,
      "per": null,
      "top10Pct": null,
      "holderOk": false,
      "ev": 7.46,
      "rr": 5.28,
      "target": 36.3,
      "stop": 17.21,
      "evPass": true,
      "status": "fail"
    },
    {
      "sid": "6434",
      "sname": "達輝光電",
      "curPrice": 18.4,
      "avgVolume": 2401.5,
      "instNet": -9.5,
      "chipScore": 2,
      "chipOk": true,
      "chipReasons": [
        "法人未買超 ✗",
        "量縮回升 ✓",
        "橫盤收斂 ✓"
      ],
      "cheapScore": 1,
      "cheapOk": false,
      "cheapReasons": [
        "距高點 52% ✓",
        "距低點 +272% ✗",
        "無 PER 資料 —"
      ],
      "high6m": 38.45,
      "low3m": 4.94,
      "dropPct": 52.1,
      "risePct": 272.5,
      "per": null,
      "top10Pct": null,
      "holderOk": false,
      "ev": 9.79,
      "rr": 7.26,
      "target": 38.45,
      "stop": 15.64,
      "evPass": true,
      "status": "fail"
    },
    {
      "sid": "6493",
      "sname": "雷虎生",
      "curPrice": 27.7,
      "avgVolume": 76.5,
      "instNet": -3.0,
      "chipScore": 2,
      "chipOk": true,
      "chipReasons": [
        "法人未買超 ✗",
        "量縮回升 ✓",
        "橫盤收斂 ✓"
      ],
      "cheapScore": 1,
      "cheapOk": false,
      "cheapReasons": [
        "距高點 40% ✓",
        "距低點 +32% ✗",
        "無 PER 資料 —"
      ],
      "high6m": 46.3,
      "low3m": 21.0,
      "dropPct": 40.2,
      "risePct": 31.9,
      "per": null,
      "top10Pct": null,
      "holderOk": false,
      "ev": 8.36,
      "rr": 4.47,
      "target": 46.3,
      "stop": 23.54,
      "evPass": true,
      "status": "fail"
    },
    {
      "sid": "5262",
      "sname": "立達",
      "curPrice": 51.0,
      "avgVolume": 215.5,
      "instNet": -16.3,
      "chipScore": 2,
      "chipOk": true,
      "chipReasons": [
        "法人未買超 ✗",
        "量縮回升 ✓",
        "橫盤收斂 ✓"
      ],
      "cheapScore": 0,
      "cheapOk": false,
      "cheapReasons": [
        "距高點僅 24% ✗",
        "距低點 +28% ✗",
        "無 PER 資料 —"
      ],
      "high6m": 66.9,
      "low3m": 39.75,
      "dropPct": 23.8,
      "risePct": 28.3,
      "per": null,
      "top10Pct": null,
      "holderOk": false,
      "ev": 5.3,
      "rr": 2.08,
      "target": 66.9,
      "stop": 43.35,
      "evPass": true,
      "status": "fail"
    },
    {
      "sid": "5267",
      "sname": "龍翩",
      "curPrice": 64.2,
      "avgVolume": 318.7,
      "instNet": 10.0,
      "chipScore": 2,
      "chipOk": true,
      "chipReasons": [
        "法人淨買超 ✓",
        "量縮回升 ✓",
        "尚未收斂 ✗"
      ],
      "cheapScore": 1,
      "cheapOk": false,
      "cheapReasons": [
        "距高點 39% ✓",
        "距低點 +156% ✗",
        "無 PER 資料 —"
      ],
      "high6m": 105.0,
      "low3m": 25.05,
      "dropPct": 38.9,
      "risePct": 156.3,
      "per": null,
      "top10Pct": null,
      "holderOk": false,
      "ev": 18.11,
      "rr": 4.24,
      "target": 105.0,
      "stop": 54.57,
      "evPass": true,
      "status": "fail"
    },
    {
      "sid": "5248",
      "sname": "景傳",
      "curPrice": 43.65,
      "avgVolume": 243.0,
      "instNet": -10.0,
      "chipScore": 2,
      "chipOk": true,
      "chipReasons": [
        "法人未買超 ✗",
        "量縮回升 ✓",
        "橫盤收斂 ✓"
      ],
      "cheapScore": 1,
      "cheapOk": false,
      "cheapReasons": [
        "距高點 65% ✓",
        "距低點 +140% ✗",
        "無 PER 資料 —"
      ],
      "high6m": 124.0,
      "low3m": 18.15,
      "dropPct": 64.8,
      "risePct": 140.5,
      "per": null,
      "top10Pct": null,
      "holderOk": false,
      "ev": 41.25,
      "rr": 12.27,
      "target": 124.0,
      "stop": 37.1,
      "evPass": true,
      "status": "fail"
    },
    {
      "sid": "5859",
      "sname": "遠壽",
      "curPrice": 13.65,
      "avgVolume": 168.8,
      "instNet": 27.0,
      "chipScore": 2,
      "chipOk": true,
      "chipReasons": [
        "法人淨買超 ✓",
        "量縮回升 ✓",
        "尚未收斂 ✗"
      ],
      "cheapScore": 1,
      "cheapOk": false,
      "cheapReasons": [
        "距高點僅 17% ✗",
        "距低點 +4% ✓",
        "無 PER 資料 —"
      ],
      "high6m": 16.35,
      "low3m": 13.15,
      "dropPct": 16.5,
      "risePct": 3.8,
      "per": null,
      "top10Pct": null,
      "holderOk": false,
      "ev": 0.56,
      "rr": 1.32,
      "target": 16.35,
      "stop": 11.6,
      "evPass": true,
      "status": "fail"
    },
    {
      "sid": "7886",
      "sname": "科建",
      "curPrice": 182.0,
      "avgVolume": 95.1,
      "instNet": 0.1,
      "chipScore": 2,
      "chipOk": true,
      "chipReasons": [
        "法人淨買超 ✓",
        "量縮回升 ✓",
        "尚未收斂 ✗"
      ],
      "cheapScore": 1,
      "cheapOk": false,
      "cheapReasons": [
        "距高點 33% ✓",
        "距低點 +33% ✗",
        "無 PER 資料 —"
      ],
      "high6m": 271.5,
      "low3m": 136.5,
      "dropPct": 33.0,
      "risePct": 33.3,
      "per": null,
      "top10Pct": null,
      "holderOk": false,
      "ev": 36.94,
      "rr": 3.28,
      "target": 271.5,
      "stop": 154.7,
      "evPass": true,
      "status": "fail"
    },
    {
      "sid": "7893",
      "sname": "睿信",
      "curPrice": 201.0,
      "avgVolume": 71.4,
      "instNet": 3.0,
      "chipScore": 2,
      "chipOk": true,
      "chipReasons": [
        "法人淨買超 ✓",
        "量縮回升 ✓",
        "尚未收斂 ✗"
      ],
      "cheapScore": 0,
      "cheapOk": false,
      "cheapReasons": [
        "距高點僅 26% ✗",
        "距低點 +24% ✗",
        "無 PER 資料 —"
      ],
      "high6m": 270.0,
      "low3m": 162.0,
      "dropPct": 25.6,
      "risePct": 24.1,
      "per": null,
      "top10Pct": null,
      "holderOk": false,
      "ev": 24.38,
      "rr": 2.29,
      "target": 270.0,
      "stop": 170.85,
      "evPass": true,
      "status": "fail"
    },
    {
      "sid": "7902",
      "sname": "宇越生醫*",
      "curPrice": 39.95,
      "avgVolume": 222.9,
      "instNet": 0.0,
      "chipScore": 2,
      "chipOk": true,
      "chipReasons": [
        "無法人資料 —",
        "量縮回升 ✓",
        "橫盤收斂 ✓"
      ],
      "cheapScore": 0,
      "cheapOk": false,
      "cheapReasons": [
        "距高點僅 22% ✗",
        "距低點 +21% ✗",
        "無 PER 資料 —"
      ],
      "high6m": 51.5,
      "low3m": 33.1,
      "dropPct": 22.4,
      "risePct": 20.7,
      "per": null,
      "top10Pct": null,
      "holderOk": false,
      "ev": 3.66,
      "rr": 1.93,
      "target": 51.5,
      "stop": 33.96,
      "evPass": true,
      "status": "fail"
    },
    {
      "sid": "7912",
      "sname": "新聿科",
      "curPrice": 576.0,
      "avgVolume": 307.0,
      "instNet": 127.0,
      "chipScore": 2,
      "chipOk": true,
      "chipReasons": [
        "法人淨買超 ✓",
        "量縮回升 ✓",
        "尚未收斂 ✗"
      ],
      "cheapScore": 1,
      "cheapOk": false,
      "cheapReasons": [
        "距高點 69% ✓",
        "距低點 +297% ✗",
        "無 PER 資料 —"
      ],
      "high6m": 1845.0,
      "low3m": 145.0,
      "dropPct": 68.8,
      "risePct": 297.2,
      "per": null,
      "top10Pct": null,
      "holderOk": false,
      "ev": 659.07,
      "rr": 14.69,
      "target": 1845.0,
      "stop": 489.6,
      "evPass": true,
      "status": "fail"
    },
    {
      "sid": "7915",
      "sname": "廌家",
      "curPrice": 691.0,
      "avgVolume": 66.6,
      "instNet": 4.4,
      "chipScore": 2,
      "chipOk": true,
      "chipReasons": [
        "法人淨買超 ✓",
        "量能型態不符 ✗",
        "橫盤收斂 ✓"
      ],
      "cheapScore": 0,
      "cheapOk": false,
      "cheapReasons": [
        "距高點僅 22% ✗",
        "距低點 +79% ✗",
        "無 PER 資料 —"
      ],
      "high6m": 883.0,
      "low3m": 386.0,
      "dropPct": 21.7,
      "risePct": 79.0,
      "per": null,
      "top10Pct": null,
      "holderOk": false,
      "ev": 58.96,
      "rr": 1.85,
      "target": 883.0,
      "stop": 587.35,
      "evPass": true,
      "status": "fail"
    },
    {
      "sid": "7856",
      "sname": "漢測",
      "curPrice": 3310.0,
      "avgVolume": 140.8,
      "instNet": 25.2,
      "chipScore": 2,
      "chipOk": true,
      "chipReasons": [
        "法人淨買超 ✓",
        "量縮回升 ✓",
        "尚未收斂 ✗"
      ],
      "cheapScore": 0,
      "cheapOk": false,
      "cheapReasons": [
        "距高點僅 17% ✗",
        "距低點 +107% ✗",
        "無 PER 資料 —"
      ],
      "high6m": 3970.0,
      "low3m": 1600.0,
      "dropPct": 16.6,
      "risePct": 106.9,
      "per": null,
      "top10Pct": null,
      "holderOk": false,
      "ev": 139.58,
      "rr": 1.33,
      "target": 3970.0,
      "stop": 2813.5,
      "evPass": true,
      "status": "fail"
    },
    {
      "sid": "7858",
      "sname": "芝普",
      "curPrice": 206.5,
      "avgVolume": 159.0,
      "instNet": 0.3,
      "chipScore": 2,
      "chipOk": true,
      "chipReasons": [
        "法人淨買超 ✓",
        "量能型態不符 ✗",
        "橫盤收斂 ✓"
      ],
      "cheapScore": 1,
      "cheapOk": false,
      "cheapReasons": [
        "距高點 40% ✓",
        "距低點 +166% ✗",
        "無 PER 資料 —"
      ],
      "high6m": 345.0,
      "low3m": 77.7,
      "dropPct": 40.1,
      "risePct": 165.8,
      "per": null,
      "top10Pct": null,
      "holderOk": false,
      "ev": 62.24,
      "rr": 4.47,
      "target": 345.0,
      "stop": 175.53,
      "evPass": true,
      "status": "fail"
    },
    {
      "sid": "7872",
      "sname": "登豐",
      "curPrice": 65.0,
      "avgVolume": 156.2,
      "instNet": -0.5,
      "chipScore": 2,
      "chipOk": true,
      "chipReasons": [
        "法人未買超 ✗",
        "量縮回升 ✓",
        "橫盤收斂 ✓"
      ],
      "cheapScore": 1,
      "cheapOk": false,
      "cheapReasons": [
        "距高點 41% ✓",
        "距低點 +98% ✗",
        "無 PER 資料 —"
      ],
      "high6m": 110.5,
      "low3m": 32.8,
      "dropPct": 41.2,
      "risePct": 98.2,
      "per": null,
      "top10Pct": null,
      "holderOk": false,
      "ev": 20.64,
      "rr": 4.67,
      "target": 110.5,
      "stop": 55.25,
      "evPass": true,
      "status": "fail"
    },
    {
      "sid": "6987",
      "sname": "寶晶能源*",
      "curPrice": 19.8,
      "avgVolume": 94.6,
      "instNet": 0.0,
      "chipScore": 2,
      "chipOk": true,
      "chipReasons": [
        "無法人資料 —",
        "量縮回升 ✓",
        "橫盤收斂 ✓"
      ],
      "cheapScore": 1,
      "cheapOk": false,
      "cheapReasons": [
        "距高點僅 22% ✗",
        "距低點 +4% ✓",
        "無 PER 資料 —"
      ],
      "high6m": 25.3,
      "low3m": 19.0,
      "dropPct": 21.7,
      "risePct": 4.2,
      "per": null,
      "top10Pct": null,
      "holderOk": false,
      "ev": 1.69,
      "rr": 1.85,
      "target": 25.3,
      "stop": 16.83,
      "evPass": true,
      "status": "fail"
    },
    {
      "sid": "7751",
      "sname": "竑騰",
      "curPrice": 1725.0,
      "avgVolume": 224.0,
      "instNet": -58.8,
      "chipScore": 1,
      "chipOk": false,
      "chipReasons": [
        "法人未買超 ✗",
        "量能型態不符 ✗",
        "橫盤收斂 ✓"
      ],
      "cheapScore": 1,
      "cheapOk": false,
      "cheapReasons": [
        "距高點 39% ✓",
        "距低點 +91% ✗",
        "PER 76.2 過高 ✗"
      ],
      "high6m": 2805.0,
      "low3m": 903.0,
      "dropPct": 38.5,
      "risePct": 91.0,
      "per": 76.16,
      "top10Pct": null,
      "holderOk": false,
      "ev": 477.56,
      "rr": 4.17,
      "target": 2805.0,
      "stop": 1466.25,
      "evPass": true,
      "status": "fail"
    },
    {
      "sid": "6968",
      "sname": "萬達寵物",
      "curPrice": 42.65,
      "avgVolume": 73.7,
      "instNet": -26.0,
      "chipScore": 1,
      "chipOk": false,
      "chipReasons": [
        "法人未買超 ✗",
        "量縮回升 ✓",
        "尚未收斂 ✗"
      ],
      "cheapScore": 2,
      "cheapOk": true,
      "cheapReasons": [
        "距高點僅 29% ✗",
        "距低點 +1% ✓",
        "PER 17.3 ✓"
      ],
      "high6m": 59.7,
      "low3m": 42.35,
      "dropPct": 28.6,
      "risePct": 0.7,
      "per": 17.34,
      "top10Pct": null,
      "holderOk": false,
      "ev": 6.5,
      "rr": 2.66,
      "target": 59.7,
      "stop": 36.25,
      "evPass": true,
      "status": "fail"
    },
    {
      "sid": "6739",
      "sname": "竹陞科技",
      "curPrice": 1255.0,
      "avgVolume": 336.4,
      "instNet": -159.1,
      "chipScore": 1,
      "chipOk": false,
      "chipReasons": [
        "法人未買超 ✗",
        "量縮回升 ✓",
        "尚未收斂 ✗"
      ],
      "cheapScore": 0,
      "cheapOk": false,
      "cheapReasons": [
        "距高點僅 29% ✗",
        "距低點 +49% ✗",
        "PER 65.7 過高 ✗"
      ],
      "high6m": 1760.0,
      "low3m": 841.0,
      "dropPct": 28.7,
      "risePct": 49.2,
      "per": 65.74,
      "top10Pct": null,
      "holderOk": false,
      "ev": 193.04,
      "rr": 2.68,
      "target": 1760.0,
      "stop": 1066.75,
      "evPass": true,
      "status": "fail"
    },
    {
      "sid": "4749",
      "sname": "新應材",
      "curPrice": 1090.0,
      "avgVolume": 2805.8,
      "instNet": -1154.0,
      "chipScore": 1,
      "chipOk": false,
      "chipReasons": [
        "法人未買超 ✗",
        "量縮回升 ✓",
        "尚未收斂 ✗"
      ],
      "cheapScore": 0,
      "cheapOk": false,
      "cheapReasons": [
        "距高點僅 10% ✗",
        "距低點 +37% ✗",
        "PER 86.0 過高 ✗"
      ],
      "high6m": 1210.0,
      "low3m": 797.0,
      "dropPct": 9.9,
      "risePct": 36.8,
      "per": 85.96,
      "top10Pct": null,
      "holderOk": false,
      "ev": -7.57,
      "rr": 0.73,
      "target": 1210.0,
      "stop": 926.5,
      "evPass": false,
      "status": "fail"
    },
    {
      "sid": "6936",
      "sname": "永鴻生技",
      "curPrice": 32.7,
      "avgVolume": 59.0,
      "instNet": -55.0,
      "chipScore": 1,
      "chipOk": false,
      "chipReasons": [
        "法人未買超 ✗",
        "量縮回升 ✓",
        "尚未收斂 ✗"
      ],
      "cheapScore": 2,
      "cheapOk": true,
      "cheapReasons": [
        "距高點僅 12% ✗",
        "距低點 +0% ✓",
        "PER 17.3 ✓"
      ],
      "high6m": 37.0,
      "low3m": 32.65,
      "dropPct": 11.6,
      "risePct": 0.2,
      "per": 17.3,
      "top10Pct": null,
      "holderOk": false,
      "ev": 0.16,
      "rr": 0.88,
      "target": 37.0,
      "stop": 27.8,
      "evPass": true,
      "status": "fail"
    },
    {
      "sid": "6925",
      "sname": "意藍",
      "curPrice": 57.8,
      "avgVolume": 67.9,
      "instNet": -98.2,
      "chipScore": 1,
      "chipOk": false,
      "chipReasons": [
        "法人未買超 ✗",
        "量縮回升 ✓",
        "尚未收斂 ✗"
      ],
      "cheapScore": 3,
      "cheapOk": true,
      "cheapReasons": [
        "距高點 49% ✓",
        "距低點 +3% ✓",
        "PER 20.3 ✓"
      ],
      "high6m": 112.5,
      "low3m": 56.3,
      "dropPct": 48.6,
      "risePct": 2.7,
      "per": 20.28,
      "top10Pct": null,
      "holderOk": false,
      "ev": 26.18,
      "rr": 6.31,
      "target": 112.5,
      "stop": 49.13,
      "evPass": true,
      "status": "fail"
    },
    {
      "sid": "6725",
      "sname": "矽科宏晟",
      "curPrice": 323.0,
      "avgVolume": 504.7,
      "instNet": -147.0,
      "chipScore": 1,
      "chipOk": false,
      "chipReasons": [
        "法人未買超 ✗",
        "量縮回升 ✓",
        "尚未收斂 ✗"
      ],
      "cheapScore": 1,
      "cheapOk": false,
      "cheapReasons": [
        "距高點僅 24% ✗",
        "距低點 +56% ✗",
        "PER 27.1 ✓"
      ],
      "high6m": 424.0,
      "low3m": 207.5,
      "dropPct": 23.8,
      "risePct": 55.7,
      "per": 27.14,
      "top10Pct": null,
      "holderOk": false,
      "ev": 33.75,
      "rr": 2.08,
      "target": 424.0,
      "stop": 274.55,
      "evPass": true,
      "status": "fail"
    },
    {
      "sid": "6403",
      "sname": "群登",
      "curPrice": 5.0,
      "avgVolume": 459.2,
      "instNet": 0.0,
      "chipScore": 1,
      "chipOk": false,
      "chipReasons": [
        "無法人資料 —",
        "量能型態不符 ✗",
        "橫盤收斂 ✓"
      ],
      "cheapScore": 2,
      "cheapOk": true,
      "cheapReasons": [
        "距高點 72% ✓",
        "距低點 +1% ✓",
        "無 PER 資料 —"
      ],
      "high6m": 17.8,
      "low3m": 4.97,
      "dropPct": 71.9,
      "risePct": 0.6,
      "per": null,
      "top10Pct": null,
      "holderOk": false,
      "ev": 6.7,
      "rr": 17.07,
      "target": 17.8,
      "stop": 4.25,
      "evPass": true,
      "status": "fail"
    },
    {
      "sid": "3616",
      "sname": "泓辰",
      "curPrice": 11.45,
      "avgVolume": 1178.0,
      "instNet": 0.0,
      "chipScore": 1,
      "chipOk": false,
      "chipReasons": [
        "無法人資料 —",
        "量能型態不符 ✗",
        "橫盤收斂 ✓"
      ],
      "cheapScore": 2,
      "cheapOk": true,
      "cheapReasons": [
        "距高點 66% ✓",
        "距低點 +19% ✓",
        "無 PER 資料 —"
      ],
      "high6m": 33.6,
      "low3m": 9.6,
      "dropPct": 65.9,
      "risePct": 19.3,
      "per": null,
      "top10Pct": null,
      "holderOk": false,
      "ev": 11.41,
      "rr": 12.88,
      "target": 33.6,
      "stop": 9.73,
      "evPass": true,
      "status": "fail"
    },
    {
      "sid": "4773",
      "sname": "高福",
      "curPrice": 39.0,
      "avgVolume": 68.0,
      "instNet": 0.0,
      "chipScore": 1,
      "chipOk": false,
      "chipReasons": [
        "無法人資料 —",
        "量縮回升 ✓",
        "尚未收斂 ✗"
      ],
      "cheapScore": 1,
      "cheapOk": false,
      "cheapReasons": [
        "距高點 42% ✓",
        "距低點 +73% ✗",
        "無 PER 資料 —"
      ],
      "high6m": 67.3,
      "low3m": 22.6,
      "dropPct": 42.1,
      "risePct": 72.6,
      "per": null,
      "top10Pct": null,
      "holderOk": false,
      "ev": 12.93,
      "rr": 4.84,
      "target": 67.3,
      "stop": 33.15,
      "evPass": true,
      "status": "fail"
    },
    {
      "sid": "7818",
      "sname": "溢泰實業",
      "curPrice": 65.9,
      "avgVolume": 1003.5,
      "instNet": 119.1,
      "chipScore": 1,
      "chipOk": false,
      "chipReasons": [
        "法人淨買超 ✓",
        "量能型態不符 ✗",
        "尚未收斂 ✗"
      ],
      "cheapScore": 3,
      "cheapOk": true,
      "cheapReasons": [
        "距高點 48% ✓",
        "距低點 +5% ✓",
        "PER 11.7 ✓"
      ],
      "high6m": 126.0,
      "low3m": 63.0,
      "dropPct": 47.7,
      "risePct": 4.6,
      "per": 11.66,
      "top10Pct": null,
      "holderOk": false,
      "ev": 28.61,
      "rr": 6.08,
      "target": 126.0,
      "stop": 56.02,
      "evPass": true,
      "status": "fail"
    },
    {
      "sid": "6983",
      "sname": "華洋精機",
      "curPrice": 385.0,
      "avgVolume": 333.8,
      "instNet": 38.6,
      "chipScore": 1,
      "chipOk": false,
      "chipReasons": [
        "法人淨買超 ✓",
        "量能型態不符 ✗",
        "尚未收斂 ✗"
      ],
      "cheapScore": 1,
      "cheapOk": false,
      "cheapReasons": [
        "距高點 30% ✓",
        "距低點 +124% ✗",
        "PER 96.5 過高 ✗"
      ],
      "high6m": 550.0,
      "low3m": 172.0,
      "dropPct": 30.0,
      "risePct": 123.8,
      "per": 96.49,
      "top10Pct": null,
      "holderOk": false,
      "ev": 64.76,
      "rr": 2.86,
      "target": 550.0,
      "stop": 327.25,
      "evPass": true,
      "status": "fail"
    },
    {
      "sid": "7819",
      "sname": "精誠金融",
      "curPrice": 45.95,
      "avgVolume": 213.5,
      "instNet": -79.0,
      "chipScore": 1,
      "chipOk": false,
      "chipReasons": [
        "法人未買超 ✗",
        "量縮回升 ✓",
        "尚未收斂 ✗"
      ],
      "cheapScore": 3,
      "cheapOk": true,
      "cheapReasons": [
        "距高點 62% ✓",
        "距低點 +1% ✓",
        "PER 15.6 ✓"
      ],
      "high6m": 120.5,
      "low3m": 45.7,
      "dropPct": 61.9,
      "risePct": 0.5,
      "per": 15.63,
      "top10Pct": null,
      "holderOk": false,
      "ev": 37.9,
      "rr": 10.82,
      "target": 120.5,
      "stop": 39.06,
      "evPass": true,
      "status": "fail"
    },
    {
      "sid": "6407",
      "sname": "相互",
      "curPrice": 33.65,
      "avgVolume": 1947.8,
      "instNet": -9.6,
      "chipScore": 1,
      "chipOk": false,
      "chipReasons": [
        "法人未買超 ✗",
        "量縮回升 ✓",
        "尚未收斂 ✗"
      ],
      "cheapScore": 1,
      "cheapOk": false,
      "cheapReasons": [
        "距高點 52% ✓",
        "距低點 +94% ✗",
        "無 PER 資料 —"
      ],
      "high6m": 69.7,
      "low3m": 17.35,
      "dropPct": 51.7,
      "risePct": 93.9,
      "per": null,
      "top10Pct": null,
      "holderOk": false,
      "ev": 17.56,
      "rr": 7.14,
      "target": 69.7,
      "stop": 28.6,
      "evPass": true,
      "status": "fail"
    },
    {
      "sid": "6549",
      "sname": "景凱",
      "curPrice": 7.82,
      "avgVolume": 161.2,
      "instNet": -9.0,
      "chipScore": 1,
      "chipOk": false,
      "chipReasons": [
        "法人未買超 ✗",
        "量縮回升 ✓",
        "尚未收斂 ✗"
      ],
      "cheapScore": 1,
      "cheapOk": false,
      "cheapReasons": [
        "距高點僅 20% ✗",
        "距低點 +9% ✓",
        "無 PER 資料 —"
      ],
      "high6m": 9.8,
      "low3m": 7.16,
      "dropPct": 20.2,
      "risePct": 9.2,
      "per": null,
      "top10Pct": null,
      "holderOk": false,
      "ev": 0.56,
      "rr": 1.69,
      "target": 9.8,
      "stop": 6.65,
      "evPass": true,
      "status": "fail"
    },
    {
      "sid": "6564",
      "sname": "安特羅",
      "curPrice": 17.0,
      "avgVolume": 82.3,
      "instNet": 0.0,
      "chipScore": 1,
      "chipOk": false,
      "chipReasons": [
        "法人未買超 ✗",
        "量縮回升 ✓",
        "尚未收斂 ✗"
      ],
      "cheapScore": 1,
      "cheapOk": false,
      "cheapReasons": [
        "距高點僅 25% ✗",
        "距低點 +6% ✓",
        "無 PER 資料 —"
      ],
      "high6m": 22.55,
      "low3m": 16.1,
      "dropPct": 24.6,
      "risePct": 5.6,
      "per": null,
      "top10Pct": null,
      "holderOk": false,
      "ev": 1.91,
      "rr": 2.18,
      "target": 22.55,
      "stop": 14.45,
      "evPass": true,
      "status": "fail"
    },
    {
      "sid": "6572",
      "sname": "博錸",
      "curPrice": 8.39,
      "avgVolume": 172.9,
      "instNet": -3.0,
      "chipScore": 1,
      "chipOk": false,
      "chipReasons": [
        "法人未買超 ✗",
        "量縮回升 ✓",
        "尚未收斂 ✗"
      ],
      "cheapScore": 1,
      "cheapOk": false,
      "cheapReasons": [
        "距高點 47% ✓",
        "距低點 +63% ✗",
        "無 PER 資料 —"
      ],
      "high6m": 15.8,
      "low3m": 5.16,
      "dropPct": 46.9,
      "risePct": 62.6,
      "per": null,
      "top10Pct": null,
      "holderOk": false,
      "ev": 3.51,
      "rr": 5.88,
      "target": 15.8,
      "stop": 7.13,
      "evPass": true,
      "status": "fail"
    },
    {
      "sid": "6473",
      "sname": "美賣*",
      "curPrice": 8.47,
      "avgVolume": 367.9,
      "instNet": -149.0,
      "chipScore": 1,
      "chipOk": false,
      "chipReasons": [
        "法人未買超 ✗",
        "量縮回升 ✓",
        "尚未收斂 ✗"
      ],
      "cheapScore": 2,
      "cheapOk": true,
      "cheapReasons": [
        "距高點 52% ✓",
        "距低點 +11% ✓",
        "無 PER 資料 —"
      ],
      "high6m": 17.5,
      "low3m": 7.66,
      "dropPct": 51.6,
      "risePct": 10.6,
      "per": null,
      "top10Pct": null,
      "holderOk": false,
      "ev": 4.39,
      "rr": 7.11,
      "target": 17.5,
      "stop": 7.2,
      "evPass": true,
      "status": "fail"
    },
    {
      "sid": "6483",
      "sname": "原創生醫",
      "curPrice": 13.15,
      "avgVolume": 77.7,
      "instNet": 0.0,
      "chipScore": 1,
      "chipOk": false,
      "chipReasons": [
        "無法人資料 —",
        "量縮回升 ✓",
        "尚未收斂 ✗"
      ],
      "cheapScore": 2,
      "cheapOk": true,
      "cheapReasons": [
        "距高點 34% ✓",
        "距低點 +4% ✓",
        "無 PER 資料 —"
      ],
      "high6m": 20.0,
      "low3m": 12.7,
      "dropPct": 34.2,
      "risePct": 3.5,
      "per": null,
      "top10Pct": null,
      "holderOk": false,
      "ev": 2.88,
      "rr": 3.48,
      "target": 20.0,
      "stop": 11.18,
      "evPass": true,
      "status": "fail"
    },
    {
      "sid": "4980",
      "sname": "佐臻",
      "curPrice": 45.65,
      "avgVolume": 880.7,
      "instNet": 5.1,
      "chipScore": 1,
      "chipOk": false,
      "chipReasons": [
        "法人淨買超 ✓",
        "量能型態不符 ✗",
        "尚未收斂 ✗"
      ],
      "cheapScore": 0,
      "cheapOk": false,
      "cheapReasons": [
        "距高點僅 21% ✗",
        "距低點 +98% ✗",
        "無 PER 資料 —"
      ],
      "high6m": 57.6,
      "low3m": 23.05,
      "dropPct": 20.7,
      "risePct": 98.0,
      "per": null,
      "top10Pct": null,
      "holderOk": false,
      "ev": 3.49,
      "rr": 1.74,
      "target": 57.6,
      "stop": 38.8,
      "evPass": true,
      "status": "fail"
    },
    {
      "sid": "5246",
      "sname": "勵威",
      "curPrice": 178.0,
      "avgVolume": 1178.9,
      "instNet": -7.2,
      "chipScore": 1,
      "chipOk": false,
      "chipReasons": [
        "法人未買超 ✗",
        "量縮回升 ✓",
        "尚未收斂 ✗"
      ],
      "cheapScore": 1,
      "cheapOk": false,
      "cheapReasons": [
        "距高點 54% ✓",
        "距低點 +273% ✗",
        "無 PER 資料 —"
      ],
      "high6m": 387.0,
      "low3m": 47.7,
      "dropPct": 54.0,
      "risePct": 273.2,
      "per": null,
      "top10Pct": null,
      "holderOk": false,
      "ev": 102.94,
      "rr": 7.83,
      "target": 387.0,
      "stop": 151.3,
      "evPass": true,
      "status": "fail"
    },
    {
      "sid": "5254",
      "sname": "欣訊科技",
      "curPrice": 44.55,
      "avgVolume": 320.5,
      "instNet": 8.0,
      "chipScore": 1,
      "chipOk": false,
      "chipReasons": [
        "法人淨買超 ✓",
        "量能型態不符 ✗",
        "尚未收斂 ✗"
      ],
      "cheapScore": 0,
      "cheapOk": false,
      "cheapReasons": [
        "距高點僅 29% ✗",
        "距低點 +46% ✗",
        "無 PER 資料 —"
      ],
      "high6m": 63.0,
      "low3m": 30.5,
      "dropPct": 29.3,
      "risePct": 46.1,
      "per": null,
      "top10Pct": null,
      "holderOk": false,
      "ev": 7.14,
      "rr": 2.76,
      "target": 63.0,
      "stop": 37.87,
      "evPass": true,
      "status": "fail"
    },
    {
      "sid": "5271",
      "sname": "紘通",
      "curPrice": 18.15,
      "avgVolume": 1308.4,
      "instNet": -206.0,
      "chipScore": 1,
      "chipOk": false,
      "chipReasons": [
        "法人未買超 ✗",
        "量縮回升 ✓",
        "尚未收斂 ✗"
      ],
      "cheapScore": 1,
      "cheapOk": false,
      "cheapReasons": [
        "距高點 67% ✓",
        "距低點 +121% ✗",
        "無 PER 資料 —"
      ],
      "high6m": 55.0,
      "low3m": 8.2,
      "dropPct": 67.0,
      "risePct": 121.3,
      "per": null,
      "top10Pct": null,
      "holderOk": false,
      "ev": 19.04,
      "rr": 13.55,
      "target": 55.0,
      "stop": 15.43,
      "evPass": true,
      "status": "fail"
    },
    {
      "sid": "7887",
      "sname": "宇川精材",
      "curPrice": 248.0,
      "avgVolume": 888.4,
      "instNet": -6.0,
      "chipScore": 1,
      "chipOk": false,
      "chipReasons": [
        "法人未買超 ✗",
        "量縮回升 ✓",
        "尚未收斂 ✗"
      ],
      "cheapScore": 1,
      "cheapOk": false,
      "cheapReasons": [
        "距高點 32% ✓",
        "距低點 +92% ✗",
        "無 PER 資料 —"
      ],
      "high6m": 366.0,
      "low3m": 129.0,
      "dropPct": 32.2,
      "risePct": 92.2,
      "per": null,
      "top10Pct": null,
      "holderOk": false,
      "ev": 48.16,
      "rr": 3.17,
      "target": 366.0,
      "stop": 210.8,
      "evPass": true,
      "status": "fail"
    },
    {
      "sid": "7888",
      "sname": "麗寶新藥",
      "curPrice": 39.5,
      "avgVolume": 127.5,
      "instNet": 0.0,
      "chipScore": 1,
      "chipOk": false,
      "chipReasons": [
        "無法人資料 —",
        "量縮回升 ✓",
        "尚未收斂 ✗"
      ],
      "cheapScore": 2,
      "cheapOk": true,
      "cheapReasons": [
        "距高點 43% ✓",
        "距低點 +11% ✓",
        "無 PER 資料 —"
      ],
      "high6m": 69.0,
      "low3m": 35.7,
      "dropPct": 42.8,
      "risePct": 10.6,
      "per": null,
      "top10Pct": null,
      "holderOk": false,
      "ev": 13.56,
      "rr": 4.97,
      "target": 69.0,
      "stop": 33.57,
      "evPass": true,
      "status": "fail"
    },
    {
      "sid": "7892",
      "sname": "元鈦科",
      "curPrice": 900.0,
      "avgVolume": 165.2,
      "instNet": 1.1,
      "chipScore": 1,
      "chipOk": false,
      "chipReasons": [
        "法人淨買超 ✓",
        "量能型態不符 ✗",
        "尚未收斂 ✗"
      ],
      "cheapScore": 1,
      "cheapOk": false,
      "cheapReasons": [
        "距高點 32% ✓",
        "距低點 +51% ✗",
        "無 PER 資料 —"
      ],
      "high6m": 1315.0,
      "low3m": 595.0,
      "dropPct": 31.6,
      "risePct": 51.3,
      "per": null,
      "top10Pct": null,
      "holderOk": false,
      "ev": 167.5,
      "rr": 3.07,
      "target": 1315.0,
      "stop": 765.0,
      "evPass": true,
      "status": "fail"
    },
    {
      "sid": "7899",
      "sname": "景美",
      "curPrice": 431.5,
      "avgVolume": 352.7,
      "instNet": -1.3,
      "chipScore": 1,
      "chipOk": false,
      "chipReasons": [
        "法人未買超 ✗",
        "量縮回升 ✓",
        "尚未收斂 ✗"
      ],
      "cheapScore": 1,
      "cheapOk": false,
      "cheapReasons": [
        "距高點 49% ✓",
        "距低點 +516% ✗",
        "無 PER 資料 —"
      ],
      "high6m": 846.0,
      "low3m": 70.0,
      "dropPct": 49.0,
      "risePct": 516.4,
      "per": null,
      "top10Pct": null,
      "holderOk": false,
      "ev": 198.85,
      "rr": 6.4,
      "target": 846.0,
      "stop": 366.77,
      "evPass": true,
      "status": "fail"
    },
    {
      "sid": "7909",
      "sname": "鈺祥",
      "curPrice": 724.0,
      "avgVolume": 282.2,
      "instNet": -35.8,
      "chipScore": 1,
      "chipOk": false,
      "chipReasons": [
        "法人未買超 ✗",
        "量縮回升 ✓",
        "尚未收斂 ✗"
      ],
      "cheapScore": 2,
      "cheapOk": true,
      "cheapReasons": [
        "距高點 34% ✓",
        "距低點 +11% ✓",
        "無 PER 資料 —"
      ],
      "high6m": 1100.0,
      "low3m": 650.0,
      "dropPct": 34.2,
      "risePct": 11.4,
      "per": null,
      "top10Pct": null,
      "holderOk": false,
      "ev": 157.93,
      "rr": 3.46,
      "target": 1100.0,
      "stop": 615.4,
      "evPass": true,
      "status": "fail"
    },
    {
      "sid": "7913",
      "sname": "通寶半導體",
      "curPrice": 274.5,
      "avgVolume": 261.9,
      "instNet": 15.0,
      "chipScore": 1,
      "chipOk": false,
      "chipReasons": [
        "法人淨買超 ✓",
        "量能型態不符 ✗",
        "歷史資料不足 —"
      ],
      "cheapScore": 1,
      "cheapOk": false,
      "cheapReasons": [
        "距高點 52% ✓",
        "距低點 +99% ✗",
        "無 PER 資料 —"
      ],
      "high6m": 573.0,
      "low3m": 138.0,
      "dropPct": 52.1,
      "risePct": 98.9,
      "per": null,
      "top10Pct": null,
      "holderOk": false,
      "ev": 145.64,
      "rr": 7.25,
      "target": 573.0,
      "stop": 233.32,
      "evPass": true,
      "status": "fail"
    },
    {
      "sid": "7880",
      "sname": "聖凰",
      "curPrice": 185.5,
      "avgVolume": 90.9,
      "instNet": 0.0,
      "chipScore": 1,
      "chipOk": false,
      "chipReasons": [
        "無法人資料 —",
        "量縮回升 ✓",
        "尚未收斂 ✗"
      ],
      "cheapScore": 1,
      "cheapOk": false,
      "cheapReasons": [
        "距高點僅 29% ✗",
        "距低點 +20% ✓",
        "無 PER 資料 —"
      ],
      "high6m": 261.5,
      "low3m": 155.0,
      "dropPct": 29.1,
      "risePct": 19.7,
      "per": null,
      "top10Pct": null,
      "holderOk": false,
      "ev": 29.28,
      "rr": 2.73,
      "target": 261.5,
      "stop": 157.67,
      "evPass": true,
      "status": "fail"
    },
    {
      "sid": "7861",
      "sname": "貝爾威勒",
      "curPrice": 1350.0,
      "avgVolume": 334.1,
      "instNet": 147.5,
      "chipScore": 1,
      "chipOk": false,
      "chipReasons": [
        "法人淨買超 ✓",
        "量能型態不符 ✗",
        "尚未收斂 ✗"
      ],
      "cheapScore": 0,
      "cheapOk": false,
      "cheapReasons": [
        "距高點僅 10% ✗",
        "距低點 +147% ✗",
        "無 PER 資料 —"
      ],
      "high6m": 1505.0,
      "low3m": 546.0,
      "dropPct": 10.3,
      "risePct": 147.3,
      "per": null,
      "top10Pct": null,
      "holderOk": false,
      "ev": -5.87,
      "rr": 0.77,
      "target": 1505.0,
      "stop": 1147.5,
      "evPass": false,
      "status": "fail"
    },
    {
      "sid": "7865",
      "sname": "金聯成",
      "curPrice": 69.2,
      "avgVolume": 236.7,
      "instNet": -3.0,
      "chipScore": 1,
      "chipOk": false,
      "chipReasons": [
        "法人未買超 ✗",
        "量縮回升 ✓",
        "尚未收斂 ✗"
      ],
      "cheapScore": 0,
      "cheapOk": false,
      "cheapReasons": [
        "距高點僅 6% ✗",
        "距低點 +69% ✗",
        "無 PER 資料 —"
      ],
      "high6m": 73.5,
      "low3m": 40.85,
      "dropPct": 5.9,
      "risePct": 69.4,
      "per": null,
      "top10Pct": null,
      "holderOk": false,
      "ev": -2.31,
      "rr": 0.41,
      "target": 73.5,
      "stop": 58.82,
      "evPass": false,
      "status": "fail"
    },
    {
      "sid": "7866",
      "sname": "丹立",
      "curPrice": 252.0,
      "avgVolume": 476.4,
      "instNet": 6.1,
      "chipScore": 1,
      "chipOk": false,
      "chipReasons": [
        "法人淨買超 ✓",
        "量能型態不符 ✗",
        "尚未收斂 ✗"
      ],
      "cheapScore": 0,
      "cheapOk": false,
      "cheapReasons": [
        "距高點僅 16% ✗",
        "距低點 +287% ✗",
        "無 PER 資料 —"
      ],
      "high6m": 300.0,
      "low3m": 65.1,
      "dropPct": 16.0,
      "risePct": 287.1,
      "per": null,
      "top10Pct": null,
      "holderOk": false,
      "ev": 9.39,
      "rr": 1.27,
      "target": 300.0,
      "stop": 214.2,
      "evPass": true,
      "status": "fail"
    },
    {
      "sid": "7871",
      "sname": "安立璽榮-KY",
      "curPrice": 68.1,
      "avgVolume": 647.6,
      "instNet": -0.5,
      "chipScore": 1,
      "chipOk": false,
      "chipReasons": [
        "法人未買超 ✗",
        "量縮回升 ✓",
        "尚未收斂 ✗"
      ],
      "cheapScore": 0,
      "cheapOk": false,
      "cheapReasons": [
        "距高點僅 26% ✗",
        "距低點 +26% ✗",
        "無 PER 資料 —"
      ],
      "high6m": 92.2,
      "low3m": 54.1,
      "dropPct": 26.1,
      "risePct": 25.9,
      "per": null,
      "top10Pct": null,
      "holderOk": false,
      "ev": 8.66,
      "rr": 2.36,
      "target": 92.2,
      "stop": 57.88,
      "evPass": true,
      "status": "fail"
    },
    {
      "sid": "6638",
      "sname": "沅聖",
      "curPrice": 53.0,
      "avgVolume": 102.8,
      "instNet": 0.0,
      "chipScore": 1,
      "chipOk": false,
      "chipReasons": [
        "法人未買超 ✗",
        "量縮回升 ✓",
        "尚未收斂 ✗"
      ],
      "cheapScore": 0,
      "cheapOk": false,
      "cheapReasons": [
        "距高點僅 27% ✗",
        "距低點 +123% ✗",
        "無 PER 資料 —"
      ],
      "high6m": 72.3,
      "low3m": 23.75,
      "dropPct": 26.7,
      "risePct": 123.2,
      "per": null,
      "top10Pct": null,
      "holderOk": false,
      "ev": 7.04,
      "rr": 2.43,
      "target": 72.3,
      "stop": 45.05,
      "evPass": true,
      "status": "fail"
    },
    {
      "sid": "6634",
      "sname": "欣耀",
      "curPrice": 66.9,
      "avgVolume": 309.6,
      "instNet": 0.0,
      "chipScore": 1,
      "chipOk": false,
      "chipReasons": [
        "無法人資料 —",
        "量縮回升 ✓",
        "尚未收斂 ✗"
      ],
      "cheapScore": 0,
      "cheapOk": false,
      "cheapReasons": [
        "距高點僅 21% ✗",
        "距低點 +130% ✗",
        "無 PER 資料 —"
      ],
      "high6m": 85.0,
      "low3m": 29.05,
      "dropPct": 21.3,
      "risePct": 130.3,
      "per": null,
      "top10Pct": null,
      "holderOk": false,
      "ev": 5.44,
      "rr": 1.8,
      "target": 85.0,
      "stop": 56.87,
      "evPass": true,
      "status": "fail"
    },
    {
      "sid": "7715",
      "sname": "裕山",
      "curPrice": 28.0,
      "avgVolume": 145.8,
      "instNet": -87.0,
      "chipScore": 0,
      "chipOk": false,
      "chipReasons": [
        "法人未買超 ✗",
        "量能型態不符 ✗",
        "尚未收斂 ✗"
      ],
      "cheapScore": 3,
      "cheapOk": true,
      "cheapReasons": [
        "距高點 36% ✓",
        "距低點 +2% ✓",
        "PER 11.7 ✓"
      ],
      "high6m": 44.0,
      "low3m": 27.5,
      "dropPct": 36.4,
      "risePct": 1.8,
      "per": 11.67,
      "top10Pct": null,
      "holderOk": false,
      "ev": 6.91,
      "rr": 3.81,
      "target": 44.0,
      "stop": 23.8,
      "evPass": true,
      "status": "fail"
    },
    {
      "sid": "7738",
      "sname": "東聯互動",
      "curPrice": 166.0,
      "avgVolume": 65.7,
      "instNet": -36.0,
      "chipScore": 0,
      "chipOk": false,
      "chipReasons": [
        "法人未買超 ✗",
        "量能型態不符 ✗",
        "尚未收斂 ✗"
      ],
      "cheapScore": 2,
      "cheapOk": true,
      "cheapReasons": [
        "距高點僅 24% ✗",
        "距低點 +4% ✓",
        "PER 11.9 ✓"
      ],
      "high6m": 219.0,
      "low3m": 160.0,
      "dropPct": 24.2,
      "risePct": 3.8,
      "per": 11.94,
      "top10Pct": null,
      "holderOk": false,
      "ev": 17.95,
      "rr": 2.13,
      "target": 219.0,
      "stop": 141.1,
      "evPass": true,
      "status": "fail"
    },
    {
      "sid": "7883",
      "sname": "饗賓",
      "curPrice": 292.0,
      "avgVolume": 71.7,
      "instNet": 0.0,
      "chipScore": 0,
      "chipOk": false,
      "chipReasons": [
        "無法人資料 —",
        "量能型態不符 ✗",
        "尚未收斂 ✗"
      ],
      "cheapScore": 0,
      "cheapOk": false,
      "cheapReasons": [
        "距高點僅 29% ✗",
        "距低點 +26% ✗",
        "無 PER 資料 —"
      ],
      "high6m": 409.0,
      "low3m": 232.0,
      "dropPct": 28.6,
      "risePct": 25.9,
      "per": null,
      "top10Pct": null,
      "holderOk": false,
      "ev": 44.64,
      "rr": 2.67,
      "target": 409.0,
      "stop": 248.2,
      "evPass": true,
      "status": "fail"
    },
    {
      "sid": "7868",
      "sname": "聖育",
      "curPrice": 95.3,
      "avgVolume": 301.8,
      "instNet": -0.0,
      "chipScore": 0,
      "chipOk": false,
      "chipReasons": [
        "法人未買超 ✗",
        "量能型態不符 ✗",
        "尚未收斂 ✗"
      ],
      "cheapScore": 0,
      "cheapOk": false,
      "cheapReasons": [
        "距高點僅 17% ✗",
        "距低點 +119% ✗",
        "無 PER 資料 —"
      ],
      "high6m": 115.0,
      "low3m": 43.55,
      "dropPct": 17.1,
      "risePct": 118.8,
      "per": null,
      "top10Pct": null,
      "holderOk": false,
      "ev": 4.4,
      "rr": 1.38,
      "target": 115.0,
      "stop": 81.0,
      "evPass": true,
      "status": "fail"
    },
    {
      "sid": "6665",
      "sname": "康聯生醫",
      "curPrice": 20.4,
      "avgVolume": 50.4,
      "instNet": -9.0,
      "chipScore": 0,
      "chipOk": false,
      "chipReasons": [
        "法人未買超 ✗",
        "量能型態不符 ✗",
        "尚未收斂 ✗"
      ],
      "cheapScore": 1,
      "cheapOk": false,
      "cheapReasons": [
        "距高點僅 16% ✗",
        "距低點 +9% ✓",
        "無 PER 資料 —"
      ],
      "high6m": 24.4,
      "low3m": 18.7,
      "dropPct": 16.4,
      "risePct": 9.1,
      "per": null,
      "top10Pct": null,
      "holderOk": false,
      "ev": 0.82,
      "rr": 1.31,
      "target": 24.4,
      "stop": 17.34,
      "evPass": true,
      "status": "fail"
    }
  ]
}